sent2vec.cpython-38-darwin.so
sent2vec_prebuilt-0.0.3.data/scripts/fasttext
sent2vec_prebuilt-0.0.3.dist-info/LICENSE
sent2vec_prebuilt-0.0.3.dist-info/METADATA
sent2vec_prebuilt-0.0.3.dist-info/WHEEL
sent2vec_prebuilt-0.0.3.dist-info/top_level.txt
sent2vec_prebuilt-0.0.3.dist-info/RECORD
