Metadata-Version: 2.1
Name: sent2vec-prebuilt
Version: 0.0.3
Summary: UNKNOWN
Home-page: https://github.com/epfml/sent2vec
Author: Pagliardini, Matteo and Gupta, Prakhar and Jaggi, Martin
License: BSD
Platform: UNKNOWN
Classifier: Programming Language :: Python :: 2.7
Classifier: Programming Language :: Python :: 3.5
Classifier: Programming Language :: Python :: 3.6
Classifier: Programming Language :: Python :: 3.7
Requires-Dist: numpy
